pyflowmeter/__init__.py
pyflowmeter/constants.py
pyflowmeter/flow.py
pyflowmeter/flow_session.py
pyflowmeter/sniffer.py
pyflowmeter/utils.py
pyflowmeter/features/__init__.py
pyflowmeter/features/flag_count.py
pyflowmeter/features/flow_bytes.py
pyflowmeter/features/packet_count.py
pyflowmeter/features/packet_length.py
pyflowmeter/features/packet_time.py
pyflowmeter/features/response_time.py
pyflowmeter/features/context/__init__.py
pyflowmeter/features/context/packet_direction.py
pyflowmeter/features/context/packet_flow_key.py
pyflowmeter-0.2.3.dist-info/LICENSE
pyflowmeter-0.2.3.dist-info/METADATA
pyflowmeter-0.2.3.dist-info/WHEEL
pyflowmeter-0.2.3.dist-info/top_level.txt
pyflowmeter-0.2.3.dist-info/RECORD
