Metadata-Version: 2.1
Name: pyflowmeter
Version: 0.2.3
Summary: CICFlowMeter V3 Python Implementation
Home-page: https://github.com/DavidRamosArchilla/pyflowmeter
Author: David Ramos Archilla
License: MIT
Platform: UNKNOWN
Classifier: License :: OSI Approved :: MIT License
Classifier: Programming Language :: Python
Classifier: Programming Language :: Python :: 3
Classifier: Programming Language :: Python :: 3.7
Classifier: Programming Language :: Python :: Implementation :: CPython
Classifier: Programming Language :: Python :: Implementation :: PyPy
Requires-Python: >=3.7.0
Requires-Dist: numpy (==1.26.1)
Requires-Dist: scipy (==1.11.3)
Requires-Dist: scapy (==2.5.0)
Requires-Dist: requests
